cyberwave_cli/__init__.py
cyberwave_cli/core.py
cyberwave_cli/setup_utils.py
cyberwave_cli/plugins/__init__.py
cyberwave_cli/plugins/loader.py
cyberwave_cli/plugins/assets/__init__.py
cyberwave_cli/plugins/assets/app.py
cyberwave_cli/plugins/auth/__init__.py
cyberwave_cli/plugins/auth/app.py
cyberwave_cli/plugins/devices/__init__.py
cyberwave_cli/plugins/devices/app.py
cyberwave_cli/plugins/edge/__init__.py
cyberwave_cli/plugins/edge/app.py
cyberwave_cli/plugins/edge/config/__init__.py
cyberwave_cli/plugins/edge/config/client.py
cyberwave_cli/plugins/edge/config/manager.py
cyberwave_cli/plugins/edge/config/schema.py
cyberwave_cli/plugins/edge/core/__init__.py
cyberwave_cli/plugins/edge/core/manager.py
cyberwave_cli/plugins/edge/core/node.py
cyberwave_cli/plugins/edge/core/runtime.py
cyberwave_cli/plugins/edge/devices/__init__.py
cyberwave_cli/plugins/edge/devices/camera_device.py
cyberwave_cli/plugins/edge/devices/nvr_camera_system.py
cyberwave_cli/plugins/edge/devices/so101_device.py
cyberwave_cli/plugins/edge/devices/spot_device.py
cyberwave_cli/plugins/edge/devices/tello_device.py
cyberwave_cli/plugins/edge/drivers/__init__.py
cyberwave_cli/plugins/edge/drivers/manager.py
cyberwave_cli/plugins/edge/processors/__init__.py
cyberwave_cli/plugins/edge/processors/base.py
cyberwave_cli/plugins/edge/processors/computer_vision.py
cyberwave_cli/plugins/edge/processors/hand_pose.py
cyberwave_cli/plugins/edge/processors/manager.py
cyberwave_cli/plugins/edge/services/__init__.py
cyberwave_cli/plugins/edge/services/cloud_client.py
cyberwave_cli/plugins/edge/services/health_monitor.py
cyberwave_cli/plugins/edge/services/video_proxy.py
cyberwave_cli/plugins/edge/utils/__init__.py
cyberwave_cli/plugins/edge/utils/backend_integration.py
cyberwave_cli/plugins/edge/utils/connectivity.py
cyberwave_cli/plugins/edge/utils/dependencies.py
cyberwave_cli/plugins/edge/utils/logger.py
cyberwave_cli/plugins/edge/utils/migration.py
cyberwave_cli/plugins/edge/utils/node_identity.py
cyberwave_cli-0.11.6.dist-info/METADATA
cyberwave_cli-0.11.6.dist-info/WHEEL
cyberwave_cli-0.11.6.dist-info/entry_points.txt
cyberwave_cli-0.11.6.dist-info/top_level.txt
cyberwave_cli-0.11.6.dist-info/RECORD
