Metadata-Version: 2.4
Name: cyberwave-cli
Version: 0.11.6
Summary: Command-line interface for the Cyberwave Digital Twin Platform - manage robots, environments, and simulations
Author-email: Cyberwave <support@cyberwave.com>
Maintainer-email: Cyberwave <support@cyberwave.com>
License: MIT
Project-URL: Homepage, https://cyberwave.com
Project-URL: Documentation, https://cyberwave.com/docs
Project-URL: Repository, https://github.com/cyberwave-os/cyberwave-cli
Project-URL: Bug Reports, https://github.com/cyberwave-os/cyberwave-cli/issues
Project-URL: Changelog, https://github.com/cyberwave-os/cyberwave-cli/releases
Keywords: robotics,digital-twin,simulation,cli,automation,robot-control
Classifier: Development Status :: 4 - Beta
Classifier: Intended Audience :: Developers
Classifier: Intended Audience :: Science/Research
Classifier: License :: OSI Approved :: MIT License
Classifier: Operating System :: OS Independent
Classifier: Programming Language :: Python :: 3
Classifier: Programming Language :: Python :: 3.8
Classifier: Programming Language :: Python :: 3.9
Classifier: Programming Language :: Python :: 3.10
Classifier: Programming Language :: Python :: 3.11
Classifier: Programming Language :: Python :: 3.12
Classifier: Topic :: Scientific/Engineering :: Artificial Intelligence
Classifier: Topic :: Software Development :: Libraries :: Python Modules
Classifier: Topic :: System :: Hardware
Requires-Python: >=3.8
Requires-Dist: typer[all]>=0.12
Requires-Dist: rich>=13
Requires-Dist: cyberwave<0.2,>=0.1
Requires-Dist: importlib_metadata>=6.0; python_version < "3.10"
Requires-Dist: setuptools>=61.0
Requires-Dist: httpx>=0.24.0
Requires-Dist: tomli>=2.0.0; python_version < "3.11"
Requires-Dist: tomli-w>=1.0.0
Provides-Extra: robotics
Requires-Dist: cyberwave-robotics-integrations<0.2,>=0.1; extra == "robotics"
Provides-Extra: test
Requires-Dist: pytest>=7.0; extra == "test"
Requires-Dist: pytest-cov; extra == "test"
Requires-Dist: pytest-mock; extra == "test"
